ffmpeg4discord/__init__.py
ffmpeg4discord/__main__.py
ffmpeg4discord/arguments.py
ffmpeg4discord/twopass.py
ffmpeg4discord/versioning.py
ffmpeg4discord/windows.py
ffmpeg4discord/templates/web.html
ffmpeg4discord-0.2.2.dist-info/licenses/LICENSE
ffmpeg4discord-0.2.2.dist-info/METADATA
ffmpeg4discord-0.2.2.dist-info/WHEEL
ffmpeg4discord-0.2.2.dist-info/entry_points.txt
ffmpeg4discord-0.2.2.dist-info/top_level.txt
ffmpeg4discord-0.2.2.dist-info/RECORD
