Metadata-Version: 2.4
Name: ffmpeg4discord
Version: 0.2.2
Summary: A tool to help convert a video file to a target file size.
Author-email: Zach Fleeman <zfleeman@gmail.com>
License-Expression: GPL-3.0-or-later
Project-URL: Homepage, https://github.com/zfleeman/ffmpeg4discord
Project-URL: Issues, https://github.com/zfleeman/ffmpeg4discord/issues
Requires-Python: >=3.9
License-File: LICENSE
Requires-Dist: Flask==3.0.1
Requires-Dist: ffmpeg-python==0.2.0
Requires-Dist: platformdirs~=4.5
Provides-Extra: dev
Requires-Dist: coverage==7.10.2; extra == "dev"
Requires-Dist: isort==6.0.1; extra == "dev"
Requires-Dist: black==25.1.0; extra == "dev"
Dynamic: license-file
